{
  "type": "Feature",
  "id": "HYDROARC 246/20(42)",
  "geometry": {
    "type": "MultiPoint",
    "coordinates": [
      [
        57.157833333333336,
        69.23183333333333
      ],
      [
        57.42216666666667,
        69.29733333333333
      ]
    ]
  },
  "properties": {
    "dtg": "2020-10-19T17:36:00",
    "raw_dtg": "191736Z OCT 20",
    "msg_id": "HYDROARC 246/20(42)",
    "cancellations": [
      "HYDROARC 9/21"
    ],
    "hazard_type": "general",
    "summary": null,
    "body": "BARENTS SEA.\nRUSSIA.\nDNC 22.\nUNDERWATER OPERATIONS IN PROGRESS UNTIL\nFURTHER NOTICE IN VICINITY:\nA. 69-13.91N 057-09.47E.\nB. 69-17.84N 057-25.33E.\nONE MILE BERTH REQUESTED."
  }
}