{
  "type": "Feature",
  "id": "HYDROARC 3100/20(56)",
  "geometry": {
    "type": "MultiPoint",
    "coordinates": [
      [
        30.868,
        33.8185
      ],
      [
        31.235,
        33.8185
      ],
      [
        31.235,
        33.6335
      ],
      [
        30.868,
        33.6335
      ]
    ]
  },
  "properties": {
    "dtg": "2020-10-12T13:58:00",
    "raw_dtg": "121358Z OCT 20",
    "msg_id": "HYDROARC 3100/20(56)",
    "cancellations": [
      "HYDROARC 3151/20"
    ],
    "hazard_type": "general",
    "summary": null,
    "body": "EASTERN MEDITERRANEAN SEA.\nCYPRUS-SOUTHWEST COAST.\nDNC 10.\n1. CABLE OPERATIONS IN PROGRESS UNTIL 22 OCT\n   BY CABLESHIP ILE D'OUESSANT IN AREA BOUND BY\n   33-49.11N 030-52.08E, 33-49.11N 031-14.10E,\n   33-38.01N 031-14.10E, 33-38.01N 030-52.08E.\n   ONE MILE BERTH REQUESTED.\n2. CANCEL HYDROLANT 2945/20.\n3. CANCEL THIS MSG 23 OCT 20."
  }
}