{
  "type": "Feature",
  "id": "HYDROARC 1172/20(53)",
  "geometry": {
    "type": "MultiPoint",
    "coordinates": [
      [
        6.435333333333333,
        40.48233333333334
      ],
      [
        6.810833333333333,
        40.7095
      ],
      [
        6.999666666666666,
        40.32866666666666
      ],
      [
        6.585333333333333,
        40.143
      ]
    ]
  },
  "properties": {
    "dtg": "2020-04-01T11:07:00",
    "raw_dtg": "011107Z APR 20",
    "msg_id": "HYDROARC 1172/20(53)",
    "cancellations": [
      "HYDROARC 1223/20"
    ],
    "hazard_type": "general",
    "summary": null,
    "body": "WESTERN MEDITERRANEAN SEA.\nSARDINIA.\nDNC 08.\n1. CABLE OPERATIONS IN PROGRESS UNTIL\n   26 APR BY CABLESHIP RAYMOND CROZE\n   IN AREA BOUND BY\n   40-28.94N 006-26.12E, 40-42.57N 006-48.65E,\n   40-19.72N 006-59.98E, 40-08.58N 006-35.12E.\n   500 METER BERTH REQUESTED.\n2. CANCEL HYDROLANT 1057/20.\n3. CANCEL THIS MSG 27 APR 20."
  }
}