{
  "type": "Feature",
  "id": "HYDROARC 1522/20(53)",
  "geometry": {
    "type": "MultiPoint",
    "coordinates": [
      [
        9.633333333333333,
        43.88333333333333
      ],
      [
        7.892333333333333,
        43.88333333333333
      ],
      [
        6.75,
        40.0
      ],
      [
        8.183333333333334,
        40.0
      ]
    ]
  },
  "properties": {
    "dtg": "2020-05-04T12:51:00",
    "raw_dtg": "041251Z MAY 20",
    "msg_id": "HYDROARC 1522/20(53)",
    "cancellations": [
      "HYDROARC 1968/20"
    ],
    "hazard_type": "general",
    "summary": null,
    "body": "WESTERN MEDITERRANEAN SEA.\nLIGURIAN SEA.\nFRANCE.\nDNC 08.\n1. SURVEY OPERATIONS 05 MAY THRU 30 JUN\n   BY M/V POURQUOI PAS IN AREA BOUND BY\n   43-53.00N 009-38.00E, 43-53.00N 007-53.54E,\n   40-00.00N 006-45.00E, 40-00.00N 008-11.00E.\n   WIDE BERTH REQUESTED.\n2. CANCEL HYDROLANT 1506/20.\n3. CANCEL THIS MSG 01 JUL 20."
  }
}