{
  "type": "Feature",
  "id": "HYDROARC 2518/20(51)",
  "geometry": {
    "type": "Point",
    "coordinates": []
  },
  "properties": {
    "dtg": "2020-08-14T14:52:00",
    "raw_dtg": "141452Z AUG 20",
    "msg_id": "HYDROARC 2518/20(51)",
    "cancellations": [
      "HYDROARC 2781/20"
    ],
    "hazard_type": "general",
    "summary": null,
    "body": "NORTH ATLANTIC.\nAZORES.\nDNC 08.\n1. SURVEY OPERATIONS 04 THRU 11 SEP BY\n   M/V THALASSA IN:\n   A. 36-15.30N 29-19.90W.\n   B. 33-27.20N 32-24.11W.\n   C. 37-35.51N 38-21.58W.\n   D. 39-25.34N 34-06.48W.\n   E. 37-04.82N 31-55.20W.\n   WIDE BERTH REQUESTED.\n2. CANCEL THIS MSG 12 SEP 20."
  }
}