{
  "type": "Feature",
  "id": "HYDROARC 3507/20(54)",
  "geometry": {
    "type": "Point",
    "coordinates": []
  },
  "properties": {
    "dtg": "2020-11-12T00:40:00",
    "raw_dtg": "120040Z NOV 20",
    "msg_id": "HYDROARC 3507/20(54)",
    "cancellations": [
      "HYDROARC 3526/20"
    ],
    "hazard_type": "general",
    "summary": null,
    "body": "AEGEAN SEA.\nDNC 09.\n1. UNDERWATER OPERATIONS BY M/V URBANO MONTI:\n   A. 12 NOV ALONG TRACKLINE JOINING\n      36-20.6N 025-28.1E, 36-39.5N 025-57.7E.\n   B. 13 AND 14 NOV ALONG TRACKLINE JOINING\n      36-39.5N 025-57.7E, 36-50.2N 026-33.6E.\n   WIDE BERTH REQUESTED.\n2. CANCEL THIS MSG 15 NOV 20."
  }
}