{
  "type": "Feature",
  "id": "HYDROARC 65/20(23,29)",
  "geometry": {
    "type": "Point",
    "coordinates": []
  },
  "properties": {
    "dtg": "2020-01-08T14:21:00",
    "raw_dtg": "081421Z JAN 20",
    "msg_id": "HYDROARC 65/20(23,29)",
    "cancellations": [
      "THIS MSG 091421Z JAN 20",
      "HYDROARC 65/20"
    ],
    "hazard_type": "general",
    "summary": null,
    "body": "SOUTH ATLANTIC.\nSCOTIA SEA.\nWEDDELL SEA.\nANTARCTICA.\nDNC 01, 29.\n1. ICEBERGS REPORTED IN:\n   A. A68A, 63-57S 053-52W.\n   B. B16, 55-56S 025-37W.\n   C. B15AA, 56-54S 031-02W.\n   D. 61-54S 052-42W.\n   E. 62-00S 052-30W.\n   F. 56-24S 035-24W.\n   G. 51-47S 024-55W.\n   H. 54-18S 029-02W.\n   I. 55-01S 027-01W.\n2. CANCEL THIS MSG 091421Z JAN 20."
  }
}