{
  "type": "Feature",
  "id": "HYDROARC 215/16(37)",
  "geometry": {
    "type": "Point",
    "coordinates": []
  },
  "properties": {
    "dtg": "2016-01-25T17:43:00",
    "raw_dtg": "251743Z JAN 16",
    "msg_id": "HYDROARC 215/16(37)",
    "cancellations": [
      "HYDROARC 221/16"
    ],
    "hazard_type": "general",
    "summary": null,
    "body": "SOUTHERN NORTH SEA.\nDNC 20, DNC 21.\nCHART 37057.\n1. ALL NAVIGATIONAL AIDS AT PLATFORMS\n   WITHIN 4.5 MILES OF 53-27N 002-20E UNRELIABLE.\n2. CANCEL HYDROLANT 3119/15."
  }
}