{
  "type": "Feature",
  "id": "HYDROARC 2062/16(12)",
  "geometry": {
    "type": "Point",
    "coordinates": []
  },
  "properties": {
    "dtg": "2016-08-14T18:53:00",
    "raw_dtg": "141853Z AUG 16",
    "msg_id": "HYDROARC 2062/16(12)",
    "cancellations": [
      "HYDROARC 2063/16"
    ],
    "hazard_type": "general",
    "summary": null,
    "body": "WESTERN NORTH ATLANTIC.\nMARYLAND.\nDNC 17.\n23 FOOT M/V MISS C.C., YELLOW HULL, TWO PERSONS ON BOARD,\nOVERDUE OCEAN CITY (38-23N 075-04W) AND RETURN.\nVESSELS IN VICINITY REQUESTED\nTO KEEP A SHARP LOOKOUT, ASSIST IF POSSIBLE.\nREPORTS TO RCC NORFOLK,\nPHONE: 757 398 6231, FAX: 757 398 6392,\nE-MAIL: D05-SMB-D5CC@USCG.MIL."
  }
}