{
  "type": "Feature",
  "id": "HYDROARC 402/16(57,61)",
  "geometry": {
    "type": "Point",
    "coordinates": []
  },
  "properties": {
    "dtg": "2016-02-17T13:32:00",
    "raw_dtg": "171332Z FEB 16",
    "msg_id": "HYDROARC 402/16(57,61)",
    "cancellations": [
      "HYDROARC 402/16"
    ],
    "hazard_type": "general",
    "summary": null,
    "body": "EASTERN SOUTH ATLANTIC.\nSOUTHWESTERN INDIAN OCEAN.\nSOUTH AFRICA.\nDNC 01, DNC 02.\nCANCEL HYDROLANT 3206/15 AND THIS MSG, SURVEY COMPLETED."
  }
}