{
  "type": "Feature",
  "id": "HYDROARC 2295/16(55)",
  "geometry": {
    "type": "Point",
    "coordinates": []
  },
  "properties": {
    "dtg": "2016-09-05T12:40:00",
    "raw_dtg": "051240Z SEP 16",
    "msg_id": "HYDROARC 2295/16(55)",
    "cancellations": [
      "THIS MSG 101900Z SEP 16",
      "HYDROARC 2295/16"
    ],
    "hazard_type": "hazardous operations",
    "summary": null,
    "body": "BLACK SEA.\nUKRAINE.\nHAZARDOUS OPERATIONS.\nDNC 10.\n1. HAZARDOUS OPERATIONS 060300Z TO 101800Z SEP\n   IN AREA BOUND BY\n   45-01.7N 036-13.5E, 44-50.8N 036-18.0E,\n   44-18.6N 036-18.0E, 44-14.0N 036-06.0E,\n   44-20.0N 035-23.0E, 44-48.0N 035-31.3E,\n   44-55.3N 035-37.5E, 45-00.4N 035-50.0E.\n2. CANCEL THIS MSG 101900Z SEP 16."
  }
}