{
  "type": "Feature",
  "id": "HYDROARC 2807/16(36,37)",
  "geometry": {
    "type": "Point",
    "coordinates": []
  },
  "properties": {
    "dtg": "2016-10-25T17:15:00",
    "raw_dtg": "251715Z OCT 16",
    "msg_id": "HYDROARC 2807/16(36,37)",
    "cancellations": [
      "THIS MSG 281715Z OCT 16",
      "HYDROARC 2826/16"
    ],
    "hazard_type": "general",
    "summary": null,
    "body": "CELTIC SEA.\nDNC 08, DNC 19.\n1. PARTIALLY SUBMERGED CONTAINER\n   ADRIFT IN 48-07N 006-45W.\n2. CANCEL THIS MSG 281715Z OCT 16."
  }
}