{
  "type": "Feature",
  "id": "HYDROARC 2899/12(51)",
  "geometry": {
    "type": "Point",
    "coordinates": []
  },
  "properties": {
    "dtg": "2012-12-08T00:09:00",
    "raw_dtg": "080009Z DEC 12",
    "msg_id": "HYDROARC 2899/12(51)",
    "cancellations": [
      "HYDROARC 3018/12"
    ],
    "hazard_type": "general",
    "summary": null,
    "body": "EASTERN NORTH ATLANTIC.\nMOROCCO.\nMAN OVERBOARD FROM F/V TALA 9 VICINITY\n34-35.2N 006-47.7W AT 072150Z DEC. VESSELS\nIN VICINITY REQUESTED TO KEEP A SHARP\nLOOKOUT, ASSIST IF POSSIBLE.\nREPORTS TO MRCC RABAT,\nPHONE: 2125 3762 5877, 2125 3762 5897,\nE-MAIL: MRCC.RABAT@MPM.GOV.MA."
  }
}