{
  "type": "Feature",
  "id": "HYDROARC 1627/12(35)",
  "geometry": {
    "type": "Point",
    "coordinates": []
  },
  "properties": {
    "dtg": "2012-07-19T09:44:00",
    "raw_dtg": "190944Z JUL 12",
    "msg_id": "HYDROARC 1627/12(35)",
    "cancellations": [
      "HYDROARC 1877/12"
    ],
    "hazard_type": "general",
    "summary": null,
    "body": "SCOTLAND-WEST COAST.\nRADIO SERVICES.\n1. MRCC BELFAST MF DSC SERVICES AT\n   TIREE 56-30N 006-59W INOPERATIVE.\n2. CANCEL HYDROLANT 1228/12."
  }
}