{
  "type": "Feature",
  "id": "HYDROARC 2438/12(24)",
  "geometry": {
    "type": "Point",
    "coordinates": []
  },
  "properties": {
    "dtg": "2012-10-18T22:26:00",
    "raw_dtg": "182226Z OCT 12",
    "msg_id": "HYDROARC 2438/12(24)",
    "cancellations": [
      "HYDROARC 2521/12"
    ],
    "hazard_type": "general",
    "summary": null,
    "body": "BRAZIL-NORTH COAST.\nVESSEL MONCAO I, TWO PERSONS ON BOARD, DISABLED\nAND ADRIFT IN 02-47S 041-22W ON 18 OCT.\nVESSELS IN VICINITY REQUESTED TO KEEP\nA SHARP LOOKOUT, ASSIST IF POSSIBLE.\nREPORTS TO ANY COASTAL RADIO STATION."
  }
}