{
  "type": "Feature",
  "id": "HYDROARC 2697/12(57)",
  "geometry": {
    "type": "Point",
    "coordinates": []
  },
  "properties": {
    "dtg": "2012-11-14T17:10:00",
    "raw_dtg": "141710Z NOV 12",
    "msg_id": "HYDROARC 2697/12(57)",
    "cancellations": [
      "HYDROARC 53/13"
    ],
    "hazard_type": "general",
    "summary": null,
    "body": "EASTERN NORTH ATLANTIC.\nGULF OF GUINEA.\nSEISMIC SURVEY IN PROGRESS UNTIL FURTHER NOTICE BY\nM/V VIKING VANQUISH TOWING 12 8000 METER LONG CABLES\nIN AREA BOUND BY\n04-38N 006-06W, 04-43N 005-50W,\n04-51N 005-22W, 04-32N 005-22W,\n04-32N 005-29W, 04-30N 005-29W.\nFIVE MILE BERTH REQUESTED."
  }
}