{
  "type": "Feature",
  "id": "NAVAREA XIX 80/21#grp6",
  "geometry": {
    "type": "Point",
    "coordinates": [
      14.5,
      73.08333333333333
    ]
  },
  "properties": {
    "parent_id": "NAVAREA XIX 80/21",
    "group_index": 6,
    "dtg": "2021-06-30T11:57:00",
    "raw_dtg": "",
    "year": 2021,
    "hazard_type": "general",
    "body": " NAVAREA XIX 80/21\n NORWEGIAN SEA\n\n 1.TESTING EXERCISES BY RUSSIAN NAVY\n FROM 302100 UTC JUN TILL 052100 UTC JUL IN AREA\n A. 71-40.0N 003-00.0E \n B. 71-40.0N 007-00.0E\n C. 69-55.0N 007-00.0E \n D. 69-55.0N 003-00.0E\n\n 2. DEEPWATER TESTING EXERCISES BY RUSSIAN NAVY\n FROM 052100 UTC JUL TILL 102100 UTC JUL IN AREA\n A. 72-24.0N 014-19.0E \n B. 73-05.0N 014-30.0E\n C. 73-03.0N 015-18.0E \n D. 72-23.0N 015-18.0E\n  ",
    "cancel_date": "2021-07-13T05:58:00",
    "valid_from": "2021-06-30T11:57:00+00:00",
    "valid_until": "2021-07-13T05:58:00",
    "summary": null
  }
}