{
  "type": "Feature",
  "id": "HYDROARC 3120/22(51)",
  "geometry": {
    "type": "Point",
    "coordinates": [
      -10.346666666666668,
      32.005
    ]
  },
  "properties": {
    "dtg": "2022-12-05T13:38:00",
    "raw_dtg": "051338Z DEC 22",
    "msg_id": "HYDROARC 3120/22(51)",
    "year": 2022,
    "cancellations": [],
    "hazard_type": "general",
    "geometry_kind": "point",
    "radius_nm": null,
    "body": "EASTERN NORTH ATLANTIC.\nMOROCCO.\nDNC 08.\nDISTRESS SIGNAL RECEIVED ON 406 MHZ FROM\nS/V BOMBAY SAPPHIRE IN 32-00.30N 010-20.80W.\nVESSELS IN VICINITY REQUESTED TO\nKEEP A SHARP LOOKOUT, ASSIST IF POSSIBLE.\nREPORTS TO MRCC RABAT,\nPHONE: 2125 3762 5877,\nFAX: 2125 3762 5017,\nE-MAIL: MRCCRABAT@GMAIL.COM.",
    "valid_from": "2022-12-05T13:38:00+00:00",
    "valid_until": null,
    "summary": null
  }
}