{
  "type": "Feature",
  "id": "HYDROARC 2523/22(37)",
  "geometry": {
    "type": "Point",
    "coordinates": [
      -7.533333333333333,
      45.13333333333333
    ]
  },
  "properties": {
    "dtg": "2022-10-05T09:19:00",
    "raw_dtg": "050919Z OCT 22",
    "msg_id": "HYDROARC 2523/22(37)",
    "cancellations": [
      "THIS MSG 080910Z OCT 22",
      "HYDROARC 2539/22"
    ],
    "hazard_type": "derelict vessel",
    "summary": null,
    "body": "EASTERN NORTH ATLANTIC.\nSPAIN.\nDNC 08.\n1. DERELICT TEN METER S/V, WHITE HULL,\n   ADRIFT IN VICINITY 45-08.00N 007-32.00W\n   AT 050800Z OCT.\n2. CANCEL HYDROLANT 2508/22.\n3. CANCEL THIS MSG 080910Z OCT 22."
  }
}