{
  "type": "Feature",
  "id": "HYDROARC 2377/22(37)#grp3",
  "geometry": {
    "type": "Point",
    "coordinates": [
      1.5238333333333334,
      55.073
    ]
  },
  "properties": {
    "parent_id": "HYDROARC 2377/22(37)",
    "group_index": 3,
    "dtg": "2022-09-20T06:32:00",
    "raw_dtg": "200632Z SEP 22",
    "year": 2022,
    "hazard_type": "general",
    "body": "NORTH SEA.\nDNC 20.\n1. UNEXPLODED ORDNANCE IN:\n   A. 54-52.04N 001-42.22E.\n   B. 54-53.72N 001-51.61E.\n   C. 55-04.38N 001-31.43E.\n2. CANCEL HYDROLANT 1976/22.",
    "cancel_date": "2022-11-01T04:58:00+00:00",
    "valid_from": "2022-09-20T06:32:00+00:00",
    "valid_until": "2022-11-01T04:58:00+00:00",
    "summary": null
  }
}