{
  "type": "Feature",
  "id": "HYDROARC 2898/22(24)",
  "geometry": {
    "type": "Point",
    "coordinates": [
      -40.66133333333333,
      -2.6853333333333333
    ]
  },
  "properties": {
    "dtg": "2022-11-12T22:38:00",
    "raw_dtg": "122238Z NOV 22",
    "msg_id": "HYDROARC 2898/22(24)",
    "cancellations": [
      "HYDROARC 3099/22"
    ],
    "hazard_type": "general",
    "summary": null,
    "body": "WESTERN SOUTH ATLANTIC.\nBRAZIL.\nDNC 01.\nMAN OVERBOARD FROM VESSEL\nIN 02-41.12S 040-39.68W ON 12 NOV.\nVESSELS IN VICINITY REQUESTED TO KEEP\nA SHARP LOOKOUT, ASSIST IF POSSIBLE.\nREPORTS TO ANY COASTAL RADIO STATION."
  }
}