{
  "type": "Feature",
  "id": "HYDROARC 1301/14(55)",
  "geometry": {
    "type": "Point",
    "coordinates": []
  },
  "properties": {
    "dtg": "2014-05-23T16:50:00",
    "raw_dtg": "231650Z MAY 14",
    "msg_id": "HYDROARC 1301/14(55)",
    "cancellations": [
      "THIS MSG 061630Z JUN 14",
      "HYDROARC 1301/14"
    ],
    "hazard_type": "hazardous operations",
    "summary": null,
    "body": "BLACK SEA.\nHAZARDOUS OPERATIONS.\n1. HAZARDOUS OPERATIONS 0700Z TO 1530Z DAILY\n   26 MAY THRU 06 JUN IN AREA BOUND BY\n   42-11N 029-24E, 42-25N 030-09E\n   41-49N 030-50E, 41-45N 030-23E.\n2. CANCEL THIS MSG 061630Z JUN 14."
  }
}