{
  "type": "Feature",
  "id": "HYDROARC 1727/14(13)",
  "geometry": null,
  "properties": {
    "dtg": "2014-07-16T04:25:00",
    "raw_dtg": "160425Z JUL 14",
    "msg_id": "HYDROARC 1727/14(13)",
    "year": 2014,
    "cancellations": [
      "HYDROARC 1815/14"
    ],
    "hazard_type": "general",
    "geometry_kind": "point",
    "radius_nm": null,
    "body": "WESTERN NORTH ATLANTIC.\nRED FLARE SIGHTED IN 39-51N 070-47W AT 160240Z JUL.\nVESSELS IN VICINITY REQUESTED TO KEEP A SHARP\nLOOKOUT, ASSIST IF POSSIBLE. REPORTS TO RCC BOSTON.\nPHONE: 617 233 8555, E-MAIL: RCCBOSTON@USCG.MIL.",
    "cancel_date": "2014-07-26T10:11:00+00:00",
    "valid_from": "2014-07-16T04:25:00+00:00",
    "valid_until": "2014-07-26T10:11:00+00:00",
    "summary": null
  }
}