{
  "type": "Feature",
  "id": "HYDROARC 1826/14(26)",
  "geometry": {
    "type": "Point",
    "coordinates": []
  },
  "properties": {
    "dtg": "2014-07-28T11:16:00",
    "raw_dtg": "281116Z JUL 14",
    "msg_id": "HYDROARC 1826/14(26)",
    "cancellations": [
      "HYDROARC 2086/14"
    ],
    "hazard_type": "general",
    "summary": null,
    "body": "WESTERN NORTH ATLANTIC.\nDISTRESS SIGNAL RECEIVED FROM 32 FOOT F/V ANNA JO,\nWHITE HULL, IN 26-58.7N 070-33.4W. VESSELS IN VICINITY\nREQUESTED TO KEEP A SHARP LOOKOUT, ASSIST IF\nPOSSIBLE. REPORTS TO U.S. COAST GUARD MIAMI,\nPHONE: 305 415 6800, E-MAIL: RCCMIAMI@USCG.MIL."
  }
}