{
  "type": "Feature",
  "id": "HYDROARC 741/11(12,13)",
  "geometry": {
    "type": "Point",
    "coordinates": []
  },
  "properties": {
    "dtg": "2011-05-01T13:52:00",
    "raw_dtg": "011352Z MAY 11",
    "msg_id": "HYDROARC 741/11(12,13)",
    "cancellations": [
      "HYDROARC 973/11"
    ],
    "hazard_type": "general",
    "summary": null,
    "body": "WESTERN NORTH ATLANTIC.\n46 FOOT S/V EVA, WHITE HULL WITH BLUE STRIPE,\nTWO PERSONS ON BOARD, UNREPORTED. LAST KNOWN\nPOSITION VICINITY 37-52N 070-12W AT 290930Z APR.\nVESSELS IN VICINITY REQUESTED TO KEEP A SHARP\nLOOKOUT, ASSIST IF POSSIBLE. REPORTS TO RCC NORFOLK,\nINMARSAT-C: 430370670, TELEX: 127775, PHONE: 757 398 6231,\nFAX: 757 398 6392, E-MAIL: D05-SMB-D5CC@USCG.MIL."
  }
}