{
  "type": "Feature",
  "id": "HYDROARC 1502/11",
  "geometry": {
    "type": "Point",
    "coordinates": []
  },
  "properties": {
    "dtg": "2011-09-17T14:10:00",
    "raw_dtg": "171410Z SEP 11",
    "msg_id": "HYDROARC 1502/11",
    "cancellations": [
      "HYDROARC 1507/11"
    ],
    "hazard_type": "general",
    "summary": null,
    "body": "NORTH ATLANTIC.\nBERMUDA TO AZORES OR IRELAND.\n36 FOOT S/V GOLDEN ANGEL, TWO PERSONS ON BOARD,\nOVERDUE BERMUDA TO AZORES OR IRELAND. VESSELS\nIN VICINITY REQUESTED TO KEEP A SHARP LOOKOUT,\nASSIST IF POSSIBLE. REPORTS TO JRCC STAVANGER,\nPHONE: 47 5151 7000, FAX: 47 5165 2334."
  }
}