{
  "type": "Feature",
  "id": "HYDROARC 601/11(44)",
  "geometry": {
    "type": "Point",
    "coordinates": []
  },
  "properties": {
    "dtg": "2011-04-11T07:24:00",
    "raw_dtg": "110724Z APR 11",
    "msg_id": "HYDROARC 601/11(44)",
    "cancellations": [
      "HYDROARC 601/11"
    ],
    "hazard_type": "hazardous operations",
    "summary": null,
    "body": "EASTERN BALTIC SEA.\nLITHUANIA.\nHAZARDOUS OPERATIONS.\n1. HAZARDOUS OPERATIONS 131000Z TO 131500Z APR\n   IN AREA BOUND BY\n   55-37N 020-46E, 55-34N 021-00E,\n   55-25N 021-00E, 55-22N 020-46E,\n   55-25N 020-42E, 55-34N 020-42E.\n2. CANCEL THIS MSG 131600Z APR."
  }
}