{
  "type": "Feature",
  "id": "HYDROARC 316/15(42)",
  "geometry": {
    "type": "Point",
    "coordinates": []
  },
  "properties": {
    "dtg": "2015-09-27T08:10:00",
    "raw_dtg": "270810Z SEP 15",
    "msg_id": "HYDROARC 316/15(42)",
    "cancellations": [
      "THIS MSG 030059Z OCT 15",
      "HYDROARC 316/15"
    ],
    "hazard_type": "hazardous operations",
    "summary": null,
    "body": "ARCTIC.\nBARENTS SEA.\nHAZARDOUS OPERATIONS.\nDNC 22.\n1. HAZARDOUS OPERATIONS 0001Z TO 2359Z\n   DAILY 30 SEP THRU 02 OCT\n   IN AREAS BOUND BY:\n   A. 72-18N 049-32E, 72-03N 050-30E,\n      68-53N 043-25E, 69-06N 042-32E.\n   B. 76-26N 055-22E, 76-16N 056-46E,\n      72-25N 050-35E, 72-32N 049-25E.\n2. CANCEL THIS MSG 030059Z OCT 15."
  }
}