{
  "type": "Feature",
  "id": "HYDROARC 2231/18(23,29)",
  "geometry": {
    "type": "Point",
    "coordinates": []
  },
  "properties": {
    "dtg": "2018-07-09T14:27:00",
    "raw_dtg": "091427Z JUL 18",
    "msg_id": "HYDROARC 2231/18(23,29)",
    "cancellations": [
      "THIS MSG 101427Z JUL 18",
      "HYDROARC 2231/18"
    ],
    "hazard_type": "general",
    "summary": null,
    "body": "WESTERN SOUTH ATLANTIC.\nSCOTIA SEA.\nDRAKE PASSAGE.\nDNC 01, DNC 07, DNC 29.\n1. ICEBERGS REPORTED IN:\n   A. B15T, 59-27S 036-06W.\n   B. C28B, 58-07S 044-21W.\n   C. 53-25S 054-01W.\n   D. 60-55S 061-21W.\n2. CANCEL THIS MSG 101427Z JUL 18."
  }
}