{
  "type": "Feature",
  "id": "HYDROARC 786/18(51)",
  "geometry": {
    "type": "Point",
    "coordinates": []
  },
  "properties": {
    "dtg": "2018-03-05T17:18:00",
    "raw_dtg": "051718Z MAR 18",
    "msg_id": "HYDROARC 786/18(51)",
    "cancellations": [
      "HYDROARC 989/18"
    ],
    "hazard_type": "general",
    "summary": null,
    "body": "EASTERN NORTH ATLANTIC.\nSENEGAL.\nDNC 01.\nM/V ANIS OVERDUE. LAST KNOWN POSITION\nIN 14-39N 017-30W AT 030340Z MAR. VESSELS IN VICINITY\nREQUESTED TO KEEP A SHARP LOOKOUT, ASSIST IF POSSIBLE.\nREPORTS TO MRCC DAKAR, PHONE: 2213 3826 5001,\nFAX: 2213 3826 5000, E-MAIL: MARINENAT@ORANGE.SN."
  }
}