{
  "type": "Feature",
  "id": "HYDROARC 2670/18(57)",
  "geometry": {
    "type": "Point",
    "coordinates": []
  },
  "properties": {
    "dtg": "2018-08-21T10:08:00",
    "raw_dtg": "211008Z AUG 18",
    "msg_id": "HYDROARC 2670/18(57)",
    "cancellations": [
      "THIS MSG 160101Z OCT 18",
      "HYDROARC 2670/18"
    ],
    "hazard_type": "general",
    "summary": null,
    "body": "GULF OF GUINEA.\nEQUATORIAL GUINEA.\nDNC 01.\n1. SURVEY OPERATIONS IN PROGRESS UNTIL 160001Z OCT\n   BY M/V RAMFORM TITAN TOWING 12 FIVE MILE LONG CABLES,\n   IN AREA BOUND BY\n   04-00.0N 008-22.0E, 03-49.0N 008-30.0E\n   03-36.0N 008-24.5E, 03-25.5N 008-11.0E\n   03-18.0N 008-11.0E, 03-00.0N 007-43.0E\n   03-20.0N 007-34.0E, 03-36.0N 007-47.0E.\n   SEVEN MILE BERTH REQUESTED.\n2. CANCEL THIS MSG 160101Z OCT 18."
  }
}