{
  "type": "Feature",
  "id": "HYDROARC 3777/18(55)",
  "geometry": {
    "type": "Point",
    "coordinates": []
  },
  "properties": {
    "dtg": "2018-12-04T15:24:00",
    "raw_dtg": "041524Z DEC 18",
    "msg_id": "HYDROARC 3777/18(55)",
    "cancellations": [
      "THIS MSG 081800Z DEC 18",
      "HYDROARC 3777/18"
    ],
    "hazard_type": "general",
    "summary": null,
    "body": "BLACK SEA.\nUKRAINE.\nDNC 10.\n1. GUNNERY EXERCISES 0600Z TO 1700Z DAILY\n   05 TRHU 08 DEC IN AREA BOUND BY\n   45-42N 032-18E, 45-49N 032-28E,\n   45-41N 032-43E, 45-34N 032-33E.\n2. CANCEL THIS MSG 081800Z DEC 18."
  }
}