{
  "type": "Feature",
  "id": "HYDROARC 3173/18(55)",
  "geometry": {
    "type": "Point",
    "coordinates": []
  },
  "properties": {
    "dtg": "2018-10-09T13:27:00",
    "raw_dtg": "091327Z OCT 18",
    "msg_id": "HYDROARC 3173/18(55)",
    "cancellations": [
      "HYDROARC 3173/18"
    ],
    "hazard_type": "general",
    "summary": null,
    "body": "BLACK SEA.\nUKRAINE.\nDNC 10.\n1. SURVEY OPERATIONS 10 THRU 31 OCT BY M/V ISKATEL\n   IN AREA BOUND BY\n   46-02.2N 030-30.6E, 46-03.0N 031-21.4E,\n   45-25.2N 031-01.5E, 45-25.3N 030-45.7E,\n   45-17.0N 030-22.2E, 45-08.0N 030-22.8E,\n   45-06.6N 030-06.4E, 45-13.9N 029-50.4E,\n   45-35.1N 029-51.5E.\n   TWO MILE BERTH REQUESTED.\n2. CANCEL THIS MSG 01 NOV 18."
  }
}