{
  "type": "Feature",
  "id": "HYDROARC 1166/10(25)",
  "geometry": {
    "type": "Point",
    "coordinates": [
      -66.90333333333334,
      24.435
    ]
  },
  "properties": {
    "dtg": "2010-06-23T17:06:00",
    "raw_dtg": "231706Z JUN 10",
    "msg_id": "HYDROARC 1166/10(25)",
    "year": 2010,
    "cancellations": [
      "HYDROARC 1358/10"
    ],
    "hazard_type": "general",
    "geometry_kind": "point",
    "radius_nm": null,
    "body": "WESTERN NORTH ATLANTIC.\nDISTRESS SIGNAL RECEIVED ON 406 MHZ IN\n24-26.1N 066-54.2W. VESSELS IN VICINITY\nREQUESTED TO KEEP A SHARP LOOKOUT, ASSIST\nIF POSSIBLE. REPORTS TO U.S. COAST GUARD SAN JUAN,\nPHONE: 787 289 2041, E-MAIL: SSJCC@USCG.MIL.",
    "cancel_date": "2010-07-17T08:57:00+00:00",
    "valid_from": "2010-06-23T17:06:00+00:00",
    "valid_until": "2010-07-17T08:57:00+00:00",
    "summary": null
  }
}