{
  "type": "Feature",
  "id": "HYDROARC 1804/10(24)",
  "geometry": {
    "type": "Point",
    "coordinates": []
  },
  "properties": {
    "dtg": "2010-09-24T03:59:00",
    "raw_dtg": "240359Z SEP 10",
    "msg_id": "HYDROARC 1804/10(24)",
    "cancellations": [
      "HYDROARC 1875/10"
    ],
    "hazard_type": "general",
    "summary": null,
    "body": "BRAZIL-NORTHEAST COAST.\nVESSEL ROMULO DISABLED AND ADRIFT REPORTS\nCREWMAN WITH BURNS REQUIRING MEDICAL\nASSISTANCE IN 03-26S 030-04W AT 232234Z SEP.\nVESSELS IN VICINITY REQUESTED TO KEEP A SHARP\nLOOKOUT, ASSIST IF POSSIBLE. REPORTS TO\nANY COASTAL RADIO STATION."
  }
}