{
  "type": "Feature",
  "id": "HYDROARC 839/15(24)",
  "geometry": {
    "type": "MultiPoint",
    "coordinates": [
      [
        -40.46666666666667,
        -22.258666666666667
      ],
      [
        -40.696333333333335,
        -22.752166666666668
      ]
    ]
  },
  "properties": {
    "dtg": "2015-04-10T01:34:00",
    "raw_dtg": "100134Z APR 15",
    "msg_id": "HYDROARC 839/15(24)",
    "cancellations": [
      "HYDROARC 839/15"
    ],
    "hazard_type": "general",
    "summary": null,
    "body": "BRAZIL-SOUTHEAST COAST.\nDNC 01.\nCHART 24160, 24008.\n1. TEN BUOYS, ORANGE, UNLIT, TEMPORARILY ESTABLISHED\n   10 APR THRU 10 JUL IN:\n   A. 22-15.52S 040-28.00W.\n   B. 22-45.13S 040-41.78W.\n   2500 METER BERTH REQUESTED.\n2. CANCEL THIS MSG 11 JUL 15."
  }
}