{
  "type": "Feature",
  "id": "HYDROARC 1113/15(36)",
  "geometry": {
    "type": "Point",
    "coordinates": []
  },
  "properties": {
    "dtg": "2015-05-07T09:39:00",
    "raw_dtg": "070939Z MAY 15",
    "msg_id": "HYDROARC 1113/15(36)",
    "cancellations": [
      "HYDROARC 1160/15"
    ],
    "hazard_type": "general",
    "summary": null,
    "body": "CELTIC SEA.\nDNC 19, DNC 20.\nUNDERWATER OPERATIONS IN PROGRESS UNTIL FURTHER\nNOTICE BY M/V ATLANTIC GUARDIAN\nVICINITY OF TRACKLINE BETWEEN\n51-17.8N 005-25.0W AND 51-17.0N 006-30.0W.\nWIDE BERTH REQUESTED."
  }
}