{
  "type": "Feature",
  "id": "HYDROARC 1984/15(44)",
  "geometry": {
    "type": "Point",
    "coordinates": []
  },
  "properties": {
    "dtg": "2015-08-14T06:36:00",
    "raw_dtg": "140636Z AUG 15",
    "msg_id": "HYDROARC 1984/15(44)",
    "cancellations": [
      "THIS MSG 220600Z AUG 15",
      "HYDROARC 1984/15"
    ],
    "hazard_type": "hazardous operations",
    "summary": null,
    "body": "EASTERN BALTIC SEA.\nLITHUANIA.\nHAZARDOUS OPERATIONS.\nDNC 22.\n1. HAZARDOUS OPERATIONS 1000Z TO 0500Z COMMENCING\n   DAILY 19 THRU 21 AUG\n   IN AREA BOUND BY\n   55-37.0N 020-46.0E, 55-35.3N 021-06.0E,\n   55-31.0N 021-05.3E, 55-25.0N 021-00.0E,\n   55-22.0N 020-46.0E, 55-25.0N 020-42.0E,\n   55-34.0N 020-42.0E.\n2. CANCEL THIS MSG 220600Z AUG 15."
  }
}