{
  "type": "Feature",
  "id": "HYDROARC 1448/15(56)",
  "geometry": {
    "type": "Point",
    "coordinates": []
  },
  "properties": {
    "dtg": "2015-06-14T10:05:00",
    "raw_dtg": "141005Z JUN 15",
    "msg_id": "HYDROARC 1448/15(56)",
    "cancellations": [
      "HYDROARC 2031/15"
    ],
    "hazard_type": "general",
    "summary": null,
    "body": "EASTERN MEDITERRANEAN SEA.\nDNC 10.\nSEISMIC SURVEY IN PROGRESS UNTIL FURTHER NOTICE BY\nM/V POLAR DUKE TOWING TEN 10000 METER LONG CABLES\nIN AREA BOUND BY\n33-33N 030-45E, 33-06N 032-41E,\n32-36N 032-39E, 32-50N 031-32E,\n33-11N 030-45E.\nSEVEN MILE BERTH REQUESTED."
  }
}