{
  "type": "Feature",
  "id": "HYDROARC 2679/15(57)",
  "geometry": {
    "type": "Point",
    "coordinates": [
      11.811166666666667,
      -15.478
    ]
  },
  "properties": {
    "dtg": "2015-10-30T15:36:00",
    "raw_dtg": "301536Z OCT 15",
    "msg_id": "HYDROARC 2679/15(57)",
    "cancellations": [
      "HYDROARC 2684/15"
    ],
    "hazard_type": "general",
    "summary": null,
    "body": "EASTERN SOUTH ATLANTIC.\nANGOLA.\nDNC 01.\nDISTRESS SIGNAL RECEIVED ON 406 MHZ FROM F/V SOUSA NOVO\nIN 15-28.68S 011-48.67E AT 300529Z OCT.\nVESSELS IN VICINITY REQUESTED TO KEEP A SHARP LOOKOUT,\nASSIST IF POSSIBLE. REPORTS TO MRCC CAPE TOWN\nOR CAPE TOWN RADIO."
  }
}