{
  "type": "Feature",
  "id": "HYDROARC 940/15(51,57)",
  "geometry": {
    "type": "Point",
    "coordinates": []
  },
  "properties": {
    "dtg": "2015-04-19T20:47:00",
    "raw_dtg": "192047Z APR 15",
    "msg_id": "HYDROARC 940/15(51,57)",
    "cancellations": [
      "THIS MSG 250016Z MAY 15",
      "HYDROARC 1007/15"
    ],
    "hazard_type": "hazardous operations",
    "summary": null,
    "body": "EASTERN NORTH ATLANTIC.\nGULF OF GUINEA.\nROCKETS.\nDNC 01.\n1. HAZARDOUS OPERATIONS 1902Z TO 2316Z DAILY\n   24 APR TO 24 MAY IN AREA BOUND BY\n   03-00N 017-27W, 01-04N 002-23W,\n   00-44S 002-37W, 01-12N 017-41W.\n2. CANCEL THIS MSG 250016Z MAY 15."
  }
}