{
  "type": "Feature",
  "id": "HYDROARC 366/24(29)",
  "geometry": {
    "type": "MultiPoint",
    "coordinates": [
      [
        -51.64,
        -60.8
      ],
      [
        -54.79,
        -72.38
      ],
      [
        -54.49,
        -65.63
      ],
      [
        -55.89,
        -65.05
      ],
      [
        -56.41,
        -65.31
      ],
      [
        -55.84,
        -72.23
      ],
      [
        -58.14,
        -65.5
      ],
      [
        -56.85,
        -65.46
      ],
      [
        -87.52,
        -72.67
      ],
      [
        -117.78,
        -71.81
      ],
      [
        -110.59,
        -73.74
      ],
      [
        -57.46,
        -69.31
      ],
      [
        -117.3,
        -72.16
      ]
    ]
  },
  "properties": {
    "dtg": "2024-02-21T16:23:00",
    "raw_dtg": "211623Z FEB 24",
    "msg_id": "HYDROARC 366/24(29)",
    "cancellations": [
      "THIS MSG 221619Z FEB 24",
      "HYDROARC 366/24"
    ],
    "hazard_type": "general",
    "summary": null,
    "body": "EASTERN SOUTH PACIFIC.\nSCOTIA SEA.\nWEDDELL SEA.\nANTARCTICA.\nDNC 29.\n1. ICEBERGS REPORTED IN:\n   A. A23A, 60-48.00S 051-38.40W.\n   B. A74A, 72-22.80S 054-47.40W.\n   C. A74B, 65-37.80S 054-29.40W.\n   D. A76B, 65-03.00S 055-53.40W.\n   E. A76C, 65-18.60S 056-24.60W.\n   F. A77, 72-13.80S 055-50.40W.\n   G. A80A, 65-30.00S 058-08.40W.\n   H. A80D, 65-27.60S 056-51.00W.\n   I. A82, 72-40.20S 087-31.20W.\n   J. B22A, 71-48.60S 117-46.80W.\n   K. B29, 73-44.40S 110-35.40W.\n   L. B39, 69-18.60S 057-27.60W.\n   M. B45, 72-09.60S 117-18.00W.\n2. CANCEL THIS MSG 221619Z FEB 24."
  }
}