{
  "type": "Feature",
  "id": "HYDROARC 981/24(36)",
  "geometry": {
    "type": "Point",
    "coordinates": [
      -7.25,
      49.0
    ]
  },
  "properties": {
    "dtg": "2024-05-10T04:19:00",
    "raw_dtg": "100419Z MAY 24",
    "msg_id": "HYDROARC 981/24(36)",
    "cancellations": [
      "HYDROARC 982/24"
    ],
    "hazard_type": "general",
    "summary": null,
    "body": "CELTIC SEA.\nENGLAND.\nDNC 19.\nDISTRESS SIGNAL RECEIVED ON 406 MHZ IN\n49-00.00N 007-15.00W. VESSELS IN VICINITY REQUESTED\nTO KEEP A SHARP LOOKOUT, ASSIST IF POSSIBLE.\nREPORTS TO MRCC FALMOUTH, PHONE: 4413 2631 7575,\nE-MAIL: FALMOUTHCOASTGUARD@MCGA.GOV.UK."
  }
}