{
  "type": "Feature",
  "id": "HYDROARC 2080/13(53,56)",
  "geometry": {
    "type": "Point",
    "coordinates": []
  },
  "properties": {
    "dtg": "2013-08-26T12:05:00",
    "raw_dtg": "261205Z AUG 13",
    "msg_id": "HYDROARC 2080/13(53,56)",
    "cancellations": [
      "HYDROARC 2121/13"
    ],
    "hazard_type": "general",
    "summary": null,
    "body": "EASTERN MEDITERRANEAN SEA.\nLIBYA.\nVESSEL, 83 PERSONS ON BOARD, IN NEED OF ASSISTANCE\nIN 33-46N 014-25E AT 261215Z AUG. VESSELS\nIN VICINITY REQUESTED TO KEEP A SHARP LOOKOUT,\nASSIST IF POSSIBLE. REPORTS TO MRCC ROME,\nINMARSAT-C: 424744220,\nPHONE: 3906 5908 4527, 3906 5908 4409,\nFAX: 3906 592 2737, 3906 5908 4793,\nE-MAIL: ITMRCC@MIT.GOV.IT."
  }
}