{
  "type": "Feature",
  "id": "HYDROARC 2932/13(24)",
  "geometry": {
    "type": "MultiPoint",
    "coordinates": [
      [
        -44.36666666666667,
        -2.3155
      ],
      [
        -44.28783333333333,
        -2.275333333333333
      ],
      [
        -44.1875,
        -2.0953333333333335
      ],
      [
        -44.37833333333333,
        -2.0953333333333335
      ]
    ]
  },
  "properties": {
    "dtg": "2013-11-20T00:50:00",
    "raw_dtg": "200050Z NOV 13",
    "msg_id": "HYDROARC 2932/13(24)",
    "cancellations": [
      "THIS MSG 032230Z DEC 13",
      "HYDROARC 2932/13"
    ],
    "hazard_type": "hazardous operations",
    "summary": null,
    "body": "BRAZIL-NORTH COAST.\nROCKETS.\n1. HAZARDOUS OPERATIONS 201300Z NOV TO 032130Z DEC\n   IN AREA BOUND BY\n   02-18.93S 044-22.00W, 02-16.52S 044-17.27W,\n   02-05.72S 044-11.25W, 02-05.72S 044-22.70W.\n2. CANCEL THIS MSG 032230Z DEC 13."
  }
}