{
  "type": "Feature",
  "id": "HYDROARC 559/13(37)",
  "geometry": {
    "type": "MultiPoint",
    "coordinates": [
      [
        -3.4143333333333334,
        50.468333333333334
      ],
      [
        -3.4126666666666665,
        50.468333333333334
      ]
    ]
  },
  "properties": {
    "dtg": "2013-03-03T06:32:00",
    "raw_dtg": "030632Z MAR 13",
    "msg_id": "HYDROARC 559/13(37)",
    "cancellations": [
      "HYDROARC 1269/13"
    ],
    "hazard_type": "general",
    "summary": null,
    "body": "ENGLAND-SOUTH COAST.\nCHART 37015\n1. DANGEROUS WRECK MARKED BY FOUR BUOYS, AL OC BU Y 0.3 SEC,\n   IN 50-28.10N 003-24.86W.\n   BUOY, RACON (D) IN 50-28.10N 003-24.76W.\n   NAVIGATION PROHIBITED WITHIN 500 METERS\n   UNLESS AUTHORIZED BY MRCC BRIXHAM.\n2. CANCEL HYDROLANT 123/13."
  }
}