{
  "type": "Feature",
  "id": "HYDROARC 921/13(51)",
  "geometry": {
    "type": "Point",
    "coordinates": []
  },
  "properties": {
    "dtg": "2013-04-12T14:30:00",
    "raw_dtg": "121430Z APR 13",
    "msg_id": "HYDROARC 921/13(51)",
    "cancellations": [
      "THIS MSG 151430Z APR 13",
      "HYDROARC 921/13"
    ],
    "hazard_type": "general",
    "summary": null,
    "body": "EASTERN NORTH ATLANTIC.\nCANARY ISLANDS.\n1. 1000 METER LONG ROPE WITH YELLOW BUOYS ADRIFT\n   VICINITY 28-40N 013-33W AT 121010Z APR.\n2. CANCEL THIS MSG 151430Z APR 13."
  }
}