{
  "type": "Feature",
  "id": "HYDROARC 3699/17(23,29)",
  "geometry": {
    "type": "Point",
    "coordinates": []
  },
  "properties": {
    "dtg": "2017-11-16T15:40:00",
    "raw_dtg": "161540Z NOV 17",
    "msg_id": "HYDROARC 3699/17(23,29)",
    "cancellations": [
      "THIS MSG 171540Z NOV 17",
      "HYDROARC 3699/17"
    ],
    "hazard_type": "general",
    "summary": null,
    "body": "WESTERN SOUTH ATLANTIC.\nSCOTIA SEA.\nDNC 01, DNC 29.\n1. ICEBERGS REPORTED IN:\n   A. B09H, 49-41S 028-35W.\n   B. B15T, 60-40S 052-23W.\n   C. B15Z, 59-02S 047-58W.\n   D. B09D, 55-04S 027-41W.\n   E. B09F, 61-55S 054-00W.\n   F. C28B, 61-53S 053-30W.\n   G. D21A, 58-34S 031-03W.\n   H. A61, 55-39S 020-48W.\n2. CANCEL THIS MSG 171540Z NOV 17."
  }
}