{
  "type": "Feature",
  "id": "HYDROARC 3376/17(55)",
  "geometry": {
    "type": "Polygon",
    "coordinates": [
      [
        [
          33.291666666666664,
          44.715
        ],
        [
          33.291666666666664,
          45.0
        ],
        [
          33.473333333333336,
          45.0
        ],
        [
          33.473333333333336,
          44.68
        ],
        [
          33.37166666666667,
          44.68
        ],
        [
          33.291666666666664,
          44.715
        ]
      ]
    ]
  },
  "properties": {
    "dtg": "2017-10-20T12:12:00",
    "raw_dtg": "201212Z OCT 17",
    "msg_id": "HYDROARC 3376/17(55)",
    "year": 2017,
    "cancellations": [
      "THIS MSG 231300Z OCT 17",
      "HYDROARC 3376/17"
    ],
    "hazard_type": "hazardous operations",
    "geometry_kind": "polygon",
    "radius_nm": null,
    "body": "BLACK SEA.\nUKRAINE.\nDNC 10.\n1. HAZARDOUS OPERATIONS 220300Z TO 231200Z OCT\n   IN AREA BOUND BY\n   44-42.9N 033-17.5E, 45-00.0N 033-17.5E,\n   45-00.0N 033-28.4E, 44-40.8N 033-28.4E,\n   44-40.8N 033-22.3E.\n2. CANCEL THIS MSG 231300Z OCT 17.",
    "cancel_date": "2017-10-23T13:00:00+00:00",
    "valid_from": "2017-10-20T12:12:00+00:00",
    "valid_until": "2017-10-23T13:00:00+00:00",
    "summary": null
  }
}