{
  "type": "Feature",
  "id": "HYDROARC 2580/17(55)",
  "geometry": {
    "type": "Point",
    "coordinates": []
  },
  "properties": {
    "dtg": "2017-08-24T14:55:00",
    "raw_dtg": "241455Z AUG 17",
    "msg_id": "HYDROARC 2580/17(55)",
    "cancellations": [
      "THIS MSG 241800Z AUG 17",
      "HYDROARC 2580/17"
    ],
    "hazard_type": "hazardous operations",
    "summary": null,
    "body": "BLACK SEA.\nUKRAINE.\nDNC 10.\n1. HAZARDOUS OPERATIONS IN PROGRESS UNTIL 241700Z AUG\n   IN AREA BOUND BY\n   44-42.9N 033-17.5E, 45-00.0N 033-17.5E,\n   45-00.0N 033-28.4E, 44-40.8N 033-28.4E,\n   44-40.8N 033-22.3E.\n2. CANCEL THIS MSG 241800Z AUG 17."
  }
}