{
  "type": "Feature",
  "id": "HYDROARC 2026/17(24)",
  "geometry": {
    "type": "MultiPoint",
    "coordinates": [
      [
        -38.972166666666666,
        -2.957
      ],
      [
        -38.975833333333334,
        -2.958
      ],
      [
        -38.95516666666666,
        -2.9735
      ],
      [
        -39.03816666666667,
        -3.025333333333333
      ],
      [
        -38.789,
        -3.0873333333333335
      ]
    ]
  },
  "properties": {
    "dtg": "2017-07-01T03:38:00",
    "raw_dtg": "010338Z JUL 17",
    "msg_id": "HYDROARC 2026/17(24)",
    "cancellations": [
      "THIS MSG 112100Z JUL 17",
      "HYDROARC 2026/17"
    ],
    "hazard_type": "general",
    "summary": null,
    "body": "WESTERN SOUTH ATLANTIC.\nBRAZIL-NORTH COAST.\nDNC 01.\n1. UNDERWATER OPERATIONS 1000Z TO 2000Z\n   01 THRU 11 JUL BY M/V OCEANICASUB V IN:\n   A. 02-57.42S 038-58.33W.\n   B. 02-57.48S 038-58.55W.\n   C. 02-58.41S 038-57.31W.\n   D. 03-01.52S 039-02.29W.\n   E. 03-05.24S 038-47.34W.\n2. CANCEL THIS MSG 112100Z JUL 17."
  }
}