{
  "type": "Feature",
  "id": "HYDROARC 4051/17(24)",
  "geometry": {
    "type": "Point",
    "coordinates": []
  },
  "properties": {
    "dtg": "2017-12-14T18:55:00",
    "raw_dtg": "141855Z DEC 17",
    "msg_id": "HYDROARC 4051/17(24)",
    "cancellations": [
      "HYDROARC 188/18"
    ],
    "hazard_type": "general",
    "summary": null,
    "body": "WESTERN SOUTH ATLANTIC.\nBRAZIL-SOUTH COAST.\nDNC 01.\nCHART 24140.\n1. ILHA DA MOELA LIGHT 24-03.0S 046-15.8W UNLIT\n   UNTIL 12 JUN 18.\n2. CANCEL THIS MSG 13 JUN 18."
  }
}