{
  "type": "Feature",
  "id": "HYDROARC 1190/23(35)",
  "geometry": {
    "type": "Point",
    "coordinates": [
      -2.8066666666666666,
      60.443333333333335
    ]
  },
  "properties": {
    "dtg": "2023-05-28T13:23:00",
    "raw_dtg": "281323Z MAY 23",
    "msg_id": "HYDROARC 1190/23(35)",
    "cancellations": [
      "HYDROARC 1223/23"
    ],
    "hazard_type": "general",
    "summary": null,
    "body": "EASTERN NORTH ATLANTIC.\nSHETLAND ISLANDS.\nDNC 20.\nCABLE OPERATIONS IN PROGRESS UNTIL FURTHER\nNOTICE BY CABLESHIP CABLE VIGILANCE IN VICINITY\n60-26.60N 002-48.40W.\nONE MILE BERTH REQUESTED."
  }
}