{
  "type": "Feature",
  "id": "HYDROARC 2660/23(35)",
  "geometry": null,
  "properties": {
    "dtg": "2023-11-19T11:15:00",
    "raw_dtg": "191115Z NOV 23",
    "msg_id": "HYDROARC 2660/23(35)",
    "year": 2023,
    "cancellations": [
      "2659/23"
    ],
    "hazard_type": "general",
    "geometry_kind": "point",
    "radius_nm": null,
    "body": "EASTERN NORTH ATLANTIC.\nSHETLAND ISLANDS.\nDNC 20.\nCANCEL HYDROLANT 2659/23 AND THIS MSG,\nSERVICE RESTORED.",
    "valid_from": "2023-11-19T11:15:00+00:00",
    "valid_until": null,
    "summary": null
  }
}