{
  "type": "Feature",
  "id": "HYDROARC 2490/23(24)",
  "geometry": {
    "type": "MultiPoint",
    "coordinates": [
      [
        -44.1345,
        -2.1048333333333336
      ],
      [
        -44.122,
        -2.046
      ],
      [
        -44.088166666666666,
        -2.0433333333333334
      ],
      [
        -44.1315,
        -2.1123333333333334
      ],
      [
        -44.14083333333333,
        -2.121166666666667
      ]
    ]
  },
  "properties": {
    "dtg": "2023-11-01T11:04:00",
    "raw_dtg": "011104Z NOV 23",
    "msg_id": "HYDROARC 2490/23(24)",
    "cancellations": [],
    "hazard_type": "general",
    "summary": null,
    "body": "WESTERN SOUTH ATLANTIC.\nBRAZIL.\nDNC 01.\nDEPTHS LESS THAN CHARTED IN:\nA. 02-06.29S 044-08.07W.\nB. 02-02.76S 044-07.32W.\nC. 02-02.60S 044-05.29W.\nD. 02-06.74S 044-07.89W.\nE. 02-07.27S 044-08.45W."
  }
}