{
  "type": "Feature",
  "id": "HYDROARC 134/23(41)",
  "geometry": {
    "type": "MultiPoint",
    "coordinates": [
      [
        107.725,
        77.40333333333334
      ],
      [
        108.71166666666667,
        77.375
      ],
      [
        108.54833333333333,
        77.39166666666667
      ],
      [
        110.08666666666667,
        77.245
      ]
    ]
  },
  "properties": {
    "dtg": "2023-07-20T11:05:00",
    "raw_dtg": "201105Z JUL 23",
    "msg_id": "HYDROARC 134/23(41)",
    "cancellations": [
      "THIS MSG 231056Z JUL 23",
      "HYDROARC 134/23"
    ],
    "hazard_type": "general",
    "summary": null,
    "body": "LAPTEV SEA.\nRUSSIA.\nDNC 27.\n1. ICEBERGS REPORTED AT 200710Z JUL IN:\n   A. 77-24.20N 107-43.50E.\n   B. 77-22.50N 108-42.70E.\n   C. 77-23.50N 108-32.90E.\n   D. 77-14.70N 110-05.20E.\n2. CANCEL THIS MSG 231056Z JUL 23."
  }
}