{
  "type": "Feature",
  "id": "HYDROARC 1541/19(24)",
  "geometry": {
    "type": "MultiPoint",
    "coordinates": [
      [
        -42.567166666666665,
        -24.898333333333333
      ],
      [
        -42.6695,
        -24.706166666666668
      ],
      [
        -42.343833333333336,
        -24.560833333333335
      ],
      [
        -42.24216666666667,
        -24.753333333333334
      ]
    ]
  },
  "properties": {
    "dtg": "2019-05-22T03:03:00",
    "raw_dtg": "220303Z MAY 19",
    "msg_id": "HYDROARC 1541/19(24)",
    "cancellations": [
      "HYDROARC 1541/19"
    ],
    "hazard_type": "general",
    "summary": null,
    "body": "WESTERN SOUTH ATLANTIC.\nBRAZIL-SOUTH COAST.\nDNC 01.\n1. SURVEY OPERATIONS IN PROGRESS UNTIL 29 MAY\n   BY M/V SUBSEA VIKING IN AREA BOUND BY\n   24-53.90S 042-34.03W, 24-42.37S 042-40.17W,\n   24-33.65S 042-20.63W, 24-45.20S 042-14.53W.\n   WIDE BERTH REQUESTED.\n2. CANCEL THIS MSG 30 MAY 19."
  }
}