{
  "type": "Feature",
  "id": "HYDROARC 226/19(23,29)",
  "geometry": {
    "type": "Point",
    "coordinates": []
  },
  "properties": {
    "dtg": "2019-01-23T16:48:00",
    "raw_dtg": "231648Z JAN 19",
    "msg_id": "HYDROARC 226/19(23,29)",
    "cancellations": [
      "THIS MSG 241648Z JAN 19",
      "HYDROARC 226/19"
    ],
    "hazard_type": "general",
    "summary": null,
    "body": "WESTERN SOUTH ATLANTIC.\nSCOTIA SEA.\nWEDDELL SEA.\nBRANSFIELD STRAIT.\nANTARCTICA.\nDNC 01, DNC 29.\n1. ICEBERGS REPORTED IN:\n   A. B15T, 54-16S 026-08W.\n   B. B09F, 60-24S 053-47W.\n   C. B16, 62-40S 043-59W.\n   D. A57A, 62-42S 059-10W.\n   E. 55-41S 047-40W.\n   F. 54-55S 035-55W.\n   G. 61-35S 035-03W.\n2. CANCEL THIS MSG 241648Z JAN 19."
  }
}