{
  "type": "Feature",
  "id": "HYDROARC 426/19(52)",
  "geometry": {
    "type": "Point",
    "coordinates": []
  },
  "properties": {
    "dtg": "2019-02-08T13:41:00",
    "raw_dtg": "081341Z FEB 19",
    "msg_id": "HYDROARC 426/19(52)",
    "cancellations": [
      "THIS MSG 111341Z FEB 19",
      "HYDROARC 426/19"
    ],
    "hazard_type": "derelict vessel",
    "summary": null,
    "body": "EASTERN MEDITERRANEAN SEA.\nTUNISIA.\nDNC 08.\n1. DERELICT F/V ADRIFT IN VICINITY\n   33-48N 011-14E AT 071740Z FEB.\n2. CANCEL THIS MSG 111341Z FEB 19."
  }
}