{
  "type": "Feature",
  "id": "HYDROARC 663/19(24)",
  "geometry": {
    "type": "Point",
    "coordinates": []
  },
  "properties": {
    "dtg": "2019-02-28T21:57:00",
    "raw_dtg": "282157Z FEB 19",
    "msg_id": "HYDROARC 663/19(24)",
    "cancellations": [
      "HYDROARC 663/19"
    ],
    "hazard_type": "general",
    "summary": null,
    "body": "WESTERN SOUTH ATLANTIC.\nBRAZIL-SOUTHEAST COAST.\nDNC 01.\n1. SURVEY OPERATIONS IN PROGRESS UNTIL 07 MAR\n   BY M/V KOMMANDOR IONA IN AREA BOUND BY\n   22-33S 040-03W, 22-36S 040-00W,\n   22-26S 039-49W, 22-19S 039-56W,\n   22-22S 039-59W, 22-24S 039-57W,\n   22-27S 040-00W, 22-29S 039-58W.\n   WIDE BERTH REQUESTED.\n2. CANCEL HYDROLANT 651/19.\n3. CANCEL THIS MSG 08 MAR 19."
  }
}