{
  "type": "Feature",
  "id": "HYDROARC 685/19(51)",
  "geometry": {
    "type": "Point",
    "coordinates": []
  },
  "properties": {
    "dtg": "2019-03-03T04:05:00",
    "raw_dtg": "030405Z MAR 19",
    "msg_id": "HYDROARC 685/19(51)",
    "cancellations": [
      "HYDROARC 918/19"
    ],
    "hazard_type": "general",
    "summary": null,
    "body": "EASTERN NORTH ATLANTIC.\nWESTERN SAHARA.\nDNC 01.\nDISTRESS SIGNAL RECEIVED FROM F/V LAMOUITTE 2\nIN VICINITY 25-52N 014-54W AT 030250Z MAR.\nVESSELS IN VICINITY REQUESTED TO KEEP A SHARP\nLOOKOUT, ASSIST IF POSSIBLE.\nREPORTS TO MRCC LAS PALMAS,\nPHONE: 349 2846 7955, 349 2846 7760,\nE-MAIL: LASPALMAS@SAASEMAR.ES."
  }
}