{
  "type": "Feature",
  "id": "HYDROARC 403/21(51)",
  "geometry": null,
  "properties": {
    "dtg": "2021-02-10T11:31:00",
    "raw_dtg": "101131Z FEB 21",
    "msg_id": "HYDROARC 403/21(51)",
    "year": 2021,
    "cancellations": [],
    "hazard_type": "general",
    "geometry_kind": "point",
    "radius_nm": null,
    "body": "EASTERN NORTH ATLANTIC.\nCANARY ISLANDS.\nDNC 01.\nNAVTEX STATION LAS PALMAS (I) 28-25.97N 16-20.17W\nUNRELIABLE.",
    "valid_from": "2021-02-10T11:31:00+00:00",
    "valid_until": null,
    "summary": null
  }
}