{
  "type": "Feature",
  "id": "HYDROARC 2576/21(37)",
  "geometry": {
    "type": "Point",
    "coordinates": [
      1.29,
      50.695
    ]
  },
  "properties": {
    "dtg": "2021-10-19T04:26:00",
    "raw_dtg": "190426Z OCT 21",
    "msg_id": "HYDROARC 2576/21(37)",
    "year": 2021,
    "cancellations": [
      "THIS MSG 220426Z OCT 21"
    ],
    "hazard_type": "general",
    "geometry_kind": "point",
    "radius_nm": null,
    "body": "DOVER STRAIT.\nFRANCE.\nDNC 20.\n1. 50 METER WIRE REPORTED ADRIFT IN VICINITY\n   OF TRACKLINE JOINING\n   50-41.7N 001-17.4E, 50-42.3N 001-17.9E.\n2. CANCEL THIS MSG 220426Z OCT 21.",
    "valid_from": "2021-10-19T04:26:00+00:00",
    "valid_until": "2021-10-22T04:26:00+00:00",
    "summary": null
  }
}