{
  "type": "Feature",
  "id": "HYDROARC 2326/21(57)",
  "geometry": {
    "type": "Point",
    "coordinates": []
  },
  "properties": {
    "dtg": "2021-09-14T14:27:00",
    "raw_dtg": "141427Z SEP 21",
    "msg_id": "HYDROARC 2326/21(57)",
    "cancellations": [
      "HYDROARC 2445/21"
    ],
    "hazard_type": "general",
    "summary": null,
    "body": "EASTERN SOUTH ATLANTIC.\nDNC 01.\nM/V AQUAVITA SEA REPORTS PERSON REQUIRING MEDICAL\nASSISTANCE IN 31-52S 002-32E AT 141400Z SEP.\nVESSELS IN VICINITY ABLE TO PROVIDE MEDICAL\nASSISTANCE REQUESTED TO ASSIST IF POSSIBLE.\nVESSELS IN VICINITY REQUESTED TO KEEP A SHARP\nLOOKOUT, ASSIST IF POSSIBLE.\nREPORTS TO MRCC CAPE TOWN, PHONE: 272 1938 3300,\nE-MAIL: MRCC.CT@SAMSA.ORG.ZA,\nMARITIMERADIO@IXMAIL.CO.ZA."
  }
}