{
  "type": "Feature",
  "id": "HYDROARC 1109/21(35)",
  "geometry": null,
  "properties": {
    "dtg": "2021-04-22T11:10:00",
    "raw_dtg": "221110Z APR 21",
    "msg_id": "HYDROARC 1109/21(35)",
    "year": 2021,
    "cancellations": [
      "1019/21",
      "HYDROARC 1109/21"
    ],
    "hazard_type": "general",
    "geometry_kind": "point",
    "radius_nm": null,
    "body": "LITTLE MINCH.\nSCOTLAND.\nDNC 19.\nCANCEL HYDROLANT 1019/21 AND THIS MSG,\nAID RESTORED.",
    "cancel_date": "2021-04-22T11:10:00+00:00",
    "valid_from": "2021-04-22T11:10:00+00:00",
    "valid_until": "2021-04-22T11:10:00+00:00",
    "summary": null
  }
}