{
  "type": "Feature",
  "id": "HYDROARC 193/21(25)",
  "geometry": {
    "type": "Point",
    "coordinates": []
  },
  "properties": {
    "dtg": "2021-01-21T07:15:00",
    "raw_dtg": "210715Z JAN 21",
    "msg_id": "HYDROARC 193/21(25)",
    "cancellations": [
      "HYDROARC 338/21"
    ],
    "hazard_type": "general",
    "summary": null,
    "body": "WESTERN NORTH ATLANTIC.\nDNC 16.\nDISTRESS SIGNAL RECEIVED FROM VESSEL GOTTLIEN\nIN 20-55N 056-41W. VESSELS IN VICINITY\nREQUESTED TO KEEP A SHARP LOOKOUT,\nASSIST IF POSSIBLE.\nREPORTS TO RSC SAN JUAN,\nPHONE: 787 289 2041,\nE-MAIL: SSJCC@USCG.MIL."
  }
}