{
  "type": "Feature",
  "id": "HYDROARC 56/16(42)",
  "geometry": {
    "type": "MultiPoint",
    "coordinates": [
      [
        39.84283333333333,
        73.85133333333333
      ],
      [
        40.75533333333333,
        74.13883333333334
      ],
      [
        41.53333333333333,
        73.96666666666667
      ],
      [
        40.615,
        73.667
      ],
      [
        43.333333333333336,
        75.625
      ],
      [
        44.9925,
        75.625
      ],
      [
        45.0,
        75.1
      ],
      [
        43.333333333333336,
        75.1
      ]
    ]
  },
  "properties": {
    "dtg": "2016-04-30T13:30:00",
    "raw_dtg": "301330Z APR 16",
    "msg_id": "HYDROARC 56/16(42)",
    "cancellations": [
      "HYDROARC 81/16"
    ],
    "hazard_type": "general",
    "summary": null,
    "body": "ARCTIC.\nBARENTS SEA.\nDNC 22.\n1. SEISMIC SURVEY IN PROGRESS UNTIL 31 OCT\n   BY M/V HAI YANG SHI YOU 720 TOWING 12\n   6400 METER LONG CABLES IN AREAS BOUND BY:\n   A. 73-51.08N 039-50.57E, 74-08.33N 040-45.32E,\n      73-58.00N 041-32.00E, 73-40.02N 040-36.90E.\n   B. 75-37.50N 043-20.00E, 75-37.50N 044-59.55E,\n      75-06.00N 045-00.00E, 75-06.00N 043-20.00E.\n   SEVEN MILE BERTH REQUESTED.\n2. CANCEL THIS MSG 01 NOV 16."
  }
}